src/__init__.py
src/advanced_questions.py
src/beginner_questions.py
src/medium_questions.py
src/quiz.py
ALU_PyQuest-0.1.8.dist-info/LICENSE
ALU_PyQuest-0.1.8.dist-info/METADATA
ALU_PyQuest-0.1.8.dist-info/WHEEL
ALU_PyQuest-0.1.8.dist-info/entry_points.txt
ALU_PyQuest-0.1.8.dist-info/top_level.txt
ALU_PyQuest-0.1.8.dist-info/RECORD
